https_roi_ciphertext/__init__.py
https_roi_ciphertext/decrypt.py
https_roi_ciphertext/encryption.py
utils/__init__.py
utils/tools.py
https_roi_ciphertext-0.0.4.dist-info/LICENSE.txt
https_roi_ciphertext-0.0.4.dist-info/METADATA
https_roi_ciphertext-0.0.4.dist-info/WHEEL
https_roi_ciphertext-0.0.4.dist-info/top_level.txt
https_roi_ciphertext-0.0.4.dist-info/RECORD
