Metadata-Version: 2.1
Name: https-roi-ciphertext
Version: 0.0.4
Summary: An feature extraction algorithm
Home-page: https://gitee.com/wxb_857_admin/https_roi_ciphertext
Author: XiaoBai
Author-email: wxok857@foxmail.com
License: MIT Licence
Keywords: pip,https_roi_ciphertext
Platform: any
Requires-Dist: pytz (==2021.1)
